scikit_activeml-0.6.2.dist-info/licenses/LICENSE.txt
skactiveml/__init__.py
skactiveml/base.py
skactiveml/exceptions.py
skactiveml/classifier/__init__.py
skactiveml/classifier/_mixture_model_classifier.py
skactiveml/classifier/_parzen_window_classifier.py
skactiveml/classifier/_wrapper.py
skactiveml/classifier/multiannotator/__init__.py
skactiveml/classifier/multiannotator/_annotator_ensemble_classifier.py
skactiveml/classifier/multiannotator/_annotator_logistic_regression.py
skactiveml/pool/__init__.py
skactiveml/pool/_badge.py
skactiveml/pool/_bald.py
skactiveml/pool/_clue.py
skactiveml/pool/_contrastive_al.py
skactiveml/pool/_core_set.py
skactiveml/pool/_cost_embedding_al.py
skactiveml/pool/_discriminative_al.py
skactiveml/pool/_drop_query.py
skactiveml/pool/_epistemic_uncertainty_sampling.py
skactiveml/pool/_expected_error_reduction.py
skactiveml/pool/_expected_model_change_maximization.py
skactiveml/pool/_expected_model_output_change.py
skactiveml/pool/_expected_model_variance.py
skactiveml/pool/_falcun.py
skactiveml/pool/_four_ds.py
skactiveml/pool/_greedy_sampling.py
skactiveml/pool/_information_gain_maximization.py
skactiveml/pool/_prob_cover.py
skactiveml/pool/_probabilistic_al.py
skactiveml/pool/_query_by_committee.py
skactiveml/pool/_quire.py
skactiveml/pool/_random_sampling.py
skactiveml/pool/_regression_tree_based_al.py
skactiveml/pool/_typi_clust.py
skactiveml/pool/_uncertainty_sampling.py
skactiveml/pool/_wrapper.py
skactiveml/pool/utils.py
skactiveml/pool/multiannotator/__init__.py
skactiveml/pool/multiannotator/_interval_estimation_threshold.py
skactiveml/pool/multiannotator/_wrapper.py
skactiveml/regressor/__init__.py
skactiveml/regressor/_nic_kernel_regressor.py
skactiveml/regressor/_wrapper.py
skactiveml/stream/__init__.py
skactiveml/stream/_density_uncertainty.py
skactiveml/stream/_stream_baselines.py
skactiveml/stream/_stream_probabilistic_al.py
skactiveml/stream/_uncertainty_zliobaite.py
skactiveml/stream/budgetmanager/__init__.py
scikit_activeml-0.6.2.dist-info/METADATA
scikit_activeml-0.6.2.dist-info/WHEEL
scikit_activeml-0.6.2.dist-info/top_level.txt
scikit_activeml-0.6.2.dist-info/RECORD
