Metadata-Version: 2.4
Name: scikit-activeml
Version: 0.6.2
Summary: scikit-activeml is a Python library for active learning on top of SciPy and scikit-learn.
Maintainer-email: Marek Herde <marek.herde@uni-kassel.de>
Project-URL: Homepage, https://scikit-activeml.github.io
Project-URL: Source, https://github.com/scikit-activeml/scikit-activeml
Keywords: active learning,machine learning,semi-supervised learning,data mining,pattern recognition,artificial intelligence
Classifier: Intended Audience :: Science/Research
Classifier: Intended Audience :: Developers
Classifier: Programming Language :: Python :: 3
Classifier: Programming Language :: Python :: 3.9
Classifier: Programming Language :: Python :: 3.10
Classifier: Programming Language :: Python :: 3.11
Classifier: Programming Language :: Python :: 3.12
Classifier: Operating System :: OS Independent
Requires-Python: >=3.9
License-File: LICENSE.txt
Requires-Dist: joblib>=1.4.0
Requires-Dist: numpy>=1.26
Requires-Dist: scipy>=1.11.3
Requires-Dist: scikit-learn>=1.6.0
Requires-Dist: matplotlib>=3.7.3
Requires-Dist: iteration-utilities>=0.12.0
Requires-Dist: makefun>=1.15.3
Provides-Extra: dev
Requires-Dist: flake8; extra == "dev"
Requires-Dist: pytest; extra == "dev"
Requires-Dist: pytest-cov; extra == "dev"
Requires-Dist: pytest-xdist; extra == "dev"
Requires-Dist: jupyter; extra == "dev"
Requires-Dist: sphinx==5.3.0; extra == "dev"
Requires-Dist: sphinxcontrib-bibtex~=2.3; extra == "dev"
Requires-Dist: numpydoc~=1.1; extra == "dev"
Requires-Dist: nbsphinx~=0.8; extra == "dev"
Requires-Dist: nbformat~=5.4.0; extra == "dev"
Requires-Dist: sphinx-gallery~=0.11; extra == "dev"
Requires-Dist: pybtex~=0.23; extra == "dev"
Requires-Dist: pydata_sphinx_theme==0.12; extra == "dev"
Requires-Dist: gitpython; extra == "dev"
Requires-Dist: black; extra == "dev"
Provides-Extra: max
Requires-Dist: joblib<=1.5.0; extra == "max"
Requires-Dist: numpy<=2.2.3; extra == "max"
Requires-Dist: scipy<=1.15.2; extra == "max"
Requires-Dist: scikit-learn<=1.6.1; extra == "max"
Requires-Dist: matplotlib<=3.10.1; extra == "max"
Requires-Dist: iteration-utilities<=0.13.0; extra == "max"
Requires-Dist: makefun<=1.16.0; extra == "max"
Dynamic: license-file
